[
  {
    "19A15101": {
      "subject_name": "Linear Algebra And Calculus",
      "units": [
        { "title": "Unit I - Matrices", "description": "Rank, Echelon form, Inverse, Linear equations.", "link": "" },
        { "title": "Unit II - Eigen Values", "description": "Eigen values, Eigen vectors, Cayley Hamilton theorem.", "link": "" },
        { "title": "Unit III - Differential Calculus", "description": "Mean value theorems, Partial derivatives, Taylor series.", "link": "" },
        { "title": "Unit IV - Multiple Integrals", "description": "Double & Triple integrals, Change of order.", "link": "" },
        { "title": "Unit V - Vector Calculus", "description": "Gradient, Divergence, Curl, Line & Surface integrals.", "link": "" }
      ],
      "textbooks": [
        { "title": "Higher Engineering Mathematics", "description":"TextBooks/Reference","author": "B.S. Grewal", "link": "" },
        { "title": "Advanced Engineering Mathematics", "description":"TextBooks/Reference","author": "Erwin Kreyszig", "link": "" }
      ],
     
      "previous_papers": [{"title":"Previous Papers","description":"Previous Papers","link":"https://google.com"}]
    }
  },

  {
    "19A15201": {
      "subject_name": "Applied Physics",
      "units": [
        { "title": "Unit I - Quantum Mechanics", "description": "Wave nature, Schrodinger equation.", "link": "" },
        { "title": "Unit II - Semiconductors", "description": "Intrinsic & Extrinsic semiconductors, PN junction.", "link": "" },
        { "title": "Unit III - Lasers", "description": "Laser principle, Types & applications.", "link": "" },
        { "title": "Unit IV - Fiber Optics", "description": "Optical fiber structure, Numerical aperture.", "link": "" },
        { "title": "Unit V - Dielectrics & Magnetics", "description": "Polarization, Magnetic materials.", "link": "" }
      ],
      "textbooks": [
        { "title": "Engineering Physics","description":"TextBooks/Reference", "author": "K. Thyagarajan", "link": "" }
      ],
     
      "previous_papers": [{"title":"Previous Papers", "description":"Previous Papers","link":"https://google.com"}]
    }
  },

  {
    "19A10501": {
      "subject_name": "Problem Solving & Programming",
      "units": [
        { "title": "Unit I - Programming Basics", "description": "Algorithms, Flowcharts, C basics.", "link": "" },
        { "title": "Unit II - Control Structures", "description": "If, Switch, Loops.", "link": "" },
        { "title": "Unit III - Functions & Arrays", "description": "Functions, Recursion, Arrays.", "link": "" },
        { "title": "Unit IV - Pointers & Strings", "description": "Pointers, String handling.", "link": "" },
        { "title": "Unit V - Structures & Files", "description": "Structures, File handling.", "link": "" }
      ],
      "textbooks": [
        { "title": "Programming in ANSI C", "description":"TextBooks/Reference","author": "E. Balagurusamy", "link": "" }
      ],
     
      "previous_papers": [{"title":"Previous Papers","description":"Previous Papers","link":"https://google.com"}]
    }
  },

  {
    "19A15501": {
      "subject_name": "Communicative English I",
      "units": [
        { "title": "Unit I - Vocabulary", "description": "Word formation, Synonyms.", "link": "" },
        { "title": "Unit II - Grammar", "description": "Tenses, Articles, Prepositions.", "link": "" },
        { "title": "Unit III - Reading Skills", "description": "Comprehension, Skimming.", "link": "" },
        { "title": "Unit IV - Writing Skills", "description": "Paragraph & Letter writing.", "link": "" },
        { "title": "Unit V - Communication Skills", "description": "Presentation & GD.", "link": "" }
      ],
      "textbooks": [
        { "title": "Technical Communication", "description":"TextBooks/Reference","author": "Meenakshi Raman", "link": "" }
      ],
     
      "previous_papers": [{"title":"Previous Papers","description":"Previous Papers","link":"https://google.com"}]
    }
  },

  {
    "19A10504": {
      "subject_name": "Computer Science & Engineering Workshop",
      "units": [],
      "textbooks": [],
     
      "previous_papers": [{"title":"Previous Papers","description":"Previous Papers","link":"https://google.com"}]
    }
  },

  {
    "19A15202": {
      "subject_name": "Applied Physics Lab",
      "units": [],
      "textbooks": [],
     
      "previous_papers": [{"title":"Previous Papers","description":"Previous Papers","link":"https://google.com"}]
    }
  },

  {
    "19A10506": {
      "subject_name": "Problem Solving & Programming Lab",
      "units": [],
      "textbooks": [],
     
      "previous_papers": [{"title":"Previous Papers","description":"Previous Papers","link":"https://google.com"}]
    }
  },

  {
    "19A15502": {
      "subject_name": "Communicative English Lab-1",
      "units": [],
      "textbooks": [],
     
      "previous_papers": [{"title":"Previous Papers","description":"Previous Papers","link":"https://google.com"}]
    }
  },
  {
    "19A10502": {
      "subject_name": "Python Programming",
      "units": [
        { "title": "Unit I - Introduction to Python", "description": "Basics, Data types, Operators.", "link": "" },
        { "title": "Unit II - Control Structures", "description": "Conditional statements, Loops.", "link": "" },
        { "title": "Unit III - Functions & Modules", "description": "Functions, Recursion, Modules.", "link": "" },
        { "title": "Unit IV - Data Structures", "description": "Lists, Tuples, Dictionaries, Sets.", "link": "" },
        { "title": "Unit V - File Handling & OOP", "description": "File operations, Classes & Objects.", "link": "" }
      ],
      "textbooks": [
        { "title": "Python Programming", "description":"TextBooks/Reference","author": "Reema Thareja", "link": "" }
      ],
     
      "previous_papers": [{"title":"Previous Papers","description":"Previous Papers","link":"https://google.com"}]
    }
  },

  {
    "19A15103": {
      "subject_name": "Probability And Statistics",
      "units": [
        { "title": "Unit I - Probability", "description": "Random variables, Probability distributions.", "link": "" },
        { "title": "Unit II - Discrete Distributions", "description": "Binomial, Poisson distributions.", "link": "" },
        { "title": "Unit III - Continuous Distributions", "description": "Normal distribution, Exponential distribution.", "link": "" },
        { "title": "Unit IV - Sampling Theory", "description": "Sampling distributions, Estimation.", "link": "" },
        { "title": "Unit V - Hypothesis Testing", "description": "Z-test, t-test, Chi-square test.", "link": "" }
      ],
      "textbooks": [
        { "title": "Probability & Statistics for Engineers", "description":"TextBooks/Reference","author": "S.C. Gupta", "link": "" }
      ],
     
      "previous_papers": [{"title":"Previous Papers","description":"Previous Papers","link":"https://google.com"}]
    }
  },

  {
    "19A15303": {
      "subject_name": "Chemistry",
      "units": [
        { "title": "Unit I - Water Technology", "description": "Hardness of water, Treatment methods.", "link": "" },
        { "title": "Unit II - Corrosion", "description": "Types of corrosion, Prevention methods.", "link": "" },
        { "title": "Unit III - Polymers", "description": "Polymerization techniques, Plastics.", "link": "" },
        { "title": "Unit IV - Energy Sources", "description": "Fuels, Batteries, Solar cells.", "link": "" },
        { "title": "Unit V - Nanomaterials", "description": "Synthesis and applications.", "link": "" }
      ],
      "textbooks": [
        { "title": "Engineering Chemistry", "description":"TextBooks/Reference","author": "P.C. Jain & Monica Jain", "link": "" }
      ],
     
      "previous_papers": [{"title":"Previous Papers","description":"Previous Papers","link":"https://google.com"}]
    }
  },

  {
    "19A10503": {
      "subject_name": "Data Structures",
      "units": [
        { "title": "Unit I - Introduction", "description": "Time complexity, Arrays, Structures.", "link": "" },
        { "title": "Unit II - Linked Lists", "description": "Singly, Doubly, Circular lists.", "link": "" },
        { "title": "Unit III - Stacks & Queues", "description": "Stack operations, Queue types.", "link": "" },
        { "title": "Unit IV - Trees", "description": "Binary trees, BST, Traversals.", "link": "" },
        { "title": "Unit V - Graphs", "description": "Graph representation, BFS, DFS.", "link": "" }
      ],
      "textbooks": [
        { "title": "Data Structures Using C", "description":"TextBooks/Reference","author": "Reema Thareja", "link": "" }
      ],
     
      "previous_papers": [{"title":"Previous Papers","description":"Previous Papers","link":"https://google.com"}]
    }
  },

  {
    "19A10303": {
      "subject_name": "Engineering Workshop",
      "units": [],
      "textbooks": [],
     
      "previous_papers": [{"title":"Previous Papers","description":"Previous Papers","link":"https://google.com"}]
    }
  },

  {
    "19A10304": {
      "subject_name": "Engineering Graphics",
      "units": [
        { "title": "Unit I - Introduction", "description": "Drawing instruments, Scales.", "link": "" },
        { "title": "Unit II - Projections", "description": "Orthographic projections.", "link": "" },
        { "title": "Unit III - Sections", "description": "Sectional views.", "link": "" },
        { "title": "Unit IV - Isometric Views", "description": "Isometric projections.", "link": "" },
        { "title": "Unit V - CAD Basics", "description": "Introduction to AutoCAD.", "link": "" }
      ],
      "textbooks": [
        { "title": "Engineering Drawing","description":"TextBooks/Reference", "author": "N.D. Bhatt", "link": "" }
      ],
     
      "previous_papers": [{"title":"Previous Papers","description":"Previous Papers","link":"https://google.com"}]
    }
  },

  {
    "19A10804": {
      "subject_name": "Environmental Science",
      "units": [
        { "title": "Unit I - Ecosystem", "description": "Structure and function.", "link": "" },
        { "title": "Unit II - Natural Resources", "description": "Water, Forest, Energy resources.", "link": "" },
        { "title": "Unit III - Biodiversity", "description": "Conservation methods.", "link": "" },
        { "title": "Unit IV - Pollution", "description": "Air, Water, Soil pollution.", "link": "" },
        { "title": "Unit V - Social Issues", "description": "Environmental laws.", "link": "" }
      ],
      "textbooks": [],
     
      "previous_papers": [{"title":"Previous Papers","description":"Previous Papers","link":"https://google.com"}]
    }
  },

  {
    "19A10508": {
      "subject_name": "Statistical Programming Lab",
      "units": [],
      "textbooks": [],
     
      "previous_papers": [{"title":"Previous Papers","description":"Previous Papers","link":"https://google.com"}]
    }
  },

  {
    "19A10505": {
      "subject_name": "Python Programming Lab",
      "units": [],
      "textbooks": [],
     
      "previous_papers": [{"title":"Previous Papers","description":"Previous Papers","link":"https://google.com"}]
    }
  },

  {
    "19A15304": {
      "subject_name": "Chemistry Lab",
      "units": [],
      "textbooks": [],
     
      "previous_papers": [{"title":"Previous Papers","description":"Previous Papers","link":"https://google.com"}]
    }
  },

  {
    "19A10507": {
      "subject_name": "Data Structures Lab",
      "units": [],
      "textbooks": [],
     
      "previous_papers": [{"title":"Previous Papers","description":"Previous Papers","link":"https://google.com"}]
    }
  }
]